#### 程序计数器

物理上是使用寄存器来实现的，寄存器是读取速度最快的一个单元，用来存储地址读取地址。

程序计数器在jvm中只是对PC寄存器的一种模拟，用来处理当前线程相关指令的计数器



```java
public static void main(String[] args) {
    int a = 11;
    int b = 22;
    int c = a + b;
    System.out.println(c);
}

      stack=2, locals=4, args_size=1
         0: bipush        11
         2: istore_1
         3: bipush        22
         5: istore_2
         6: iload_1
         7: iload_2
         8: iadd
         9: istore_3
        10: getstatic     #7       // Field java/lang/System.out:Ljava/io/PrintStream;
        13: iload_3
        14: invokevirtual #13      // Method java/io/PrintStream.println:(I)V
        17: return
```

问题一：使用PC寄存器存储字节码指令地址有什么用？

cpu需要不停切换各个线程，这时候切换回来以后，就得知道接着从那开始继续执行。具体来说就是jvm的字节码解释器就需要通过改变pc寄存器的值来明确下一条应该执行什么的字节码指令。

问题二:pc寄存器为什么被设定为私有的

所谓的多线程是指在特定时间内执行某一个线程的方法，cpu会不断切换任务，这样必然导致经常中断或恢复，为了能够准确的记录各个线程正在执行的当前字节码指令地址，最好的办法是为了每一个线程都分配一个pc寄存器这样一来各个线程便可进行独立计算从而不会出现相互干扰的情况。







#### jdk动态代理



```
/*
todo方法怎么在invoke方法中调用的
 */

/*
  利用o.getClass().getClassLoader(),o.getClass().getInterfaces(),handler接口里的方法加载到一个虚拟类里
  然后里边有应用类加载器可以加载这个虚拟类，虚拟类里有handler，可以调用handler.invoke()方法
 */

/*
  调用jdk创造的虚拟类里的todo方法，在虚拟类里的invoke方法
  通过方法名和参数（Object result = method.invoke(o, args);）确定唯一逻辑
 */
```



